[{"taskId":"glyJu2Wmd","title":"xxxxx","status":"done","_isDeleted":false,"_createdAt":1601542402603,"_deletedAt":null},{"taskId":"t6NLkhmgw","title":"ccccc","status":"done","_isDeleted":false,"_createdAt":1601542404652,"_deletedAt":null},{"taskId":"Z-1ytmm7G","title":"vvvvv","status":"done","_isDeleted":false,"_createdAt":1601542406575,"_deletedAt":null},{"taskId":"dAbXHXcPN","title":"xczxc","status":"done","_isDeleted":false,"_createdAt":1601542470969,"_deletedAt":null},{"taskId":"CzbttQ-bv","title":"cvxcv","status":"done","_isDeleted":false,"_createdAt":1601542481609,"_deletedAt":null}]